avirtech_autoexport/__init__.py
avirtech_autoexport/avirtech_autoexport.py
avirtech_autoexport-0.1.0.dist-info/METADATA
avirtech_autoexport-0.1.0.dist-info/WHEEL
avirtech_autoexport-0.1.0.dist-info/top_level.txt
avirtech_autoexport-0.1.0.dist-info/RECORD
