Metadata-Version: 2.1
Name: avirtech-autoexport
Version: 0.1.0
Summary: Avirtech Autoexport Library on Agisoft Metashape to generate data and report based on clients requirement
Home-page: https://github.com/dwieka21-bit
Author: Dwieka
Author-email: patriadwieka@gmail.com
License: MIT
Platform: UNKNOWN
Classifier: Intended Audience :: Developers
Classifier: License :: OSI Approved :: MIT License
Classifier: Programming Language :: Python
Classifier: Programming Language :: Python :: 3
Classifier: Programming Language :: Python :: 3.6
Classifier: Programming Language :: Python :: 3.7
Classifier: Programming Language :: Python :: 3.8
Classifier: Programming Language :: Python :: 3.9
Classifier: Operating System :: OS Independent
Requires-Dist: csv-metashape-generator-2
Requires-Dist: pywin32
